odoo/addons/account_payment_other_company/README.rst
odoo/addons/account_payment_other_company/__init__.py
odoo/addons/account_payment_other_company/__manifest__.py
odoo/addons/account_payment_other_company/i18n/account_payment_other_company.pot
odoo/addons/account_payment_other_company/models/__init__.py
odoo/addons/account_payment_other_company/models/account_journal.py
odoo/addons/account_payment_other_company/models/account_payment.py
odoo/addons/account_payment_other_company/readme/CONFIGURE.rst
odoo/addons/account_payment_other_company/readme/CONTRIBUTORS.rst
odoo/addons/account_payment_other_company/readme/CREDITS.rst
odoo/addons/account_payment_other_company/readme/DESCRIPTION.rst
odoo/addons/account_payment_other_company/readme/USAGE.rst
odoo/addons/account_payment_other_company/static/description/icon.png
odoo/addons/account_payment_other_company/static/description/index.html
odoo/addons/account_payment_other_company/tests/__init__.py
odoo/addons/account_payment_other_company/tests/test_account_payment.py
odoo/addons/account_payment_other_company/tests/test_account_payment_data.xml
odoo/addons/account_payment_other_company/views/account_payment.xml
odoo/addons/account_payment_other_company/wizard/__init__.py
odoo/addons/account_payment_other_company/wizard/account_register_payments.py
odoo/addons/account_payment_other_company/wizard/account_register_payments.xml
odoo14_addon_account_payment_other_company-14.0.1.0.2.dist-info/METADATA
odoo14_addon_account_payment_other_company-14.0.1.0.2.dist-info/WHEEL
odoo14_addon_account_payment_other_company-14.0.1.0.2.dist-info/top_level.txt
odoo14_addon_account_payment_other_company-14.0.1.0.2.dist-info/RECORD
